PyLFMF-1.1.1.dist-info/LICENSE
PyLFMF-1.1.1.dist-info/METADATA
PyLFMF-1.1.1.dist-info/top_level.txt
PyLFMF-1.1.1.dist-info/WHEEL
PyLFMF-1.1.1.dist-info/RECORD
PyLFMF/module.py
PyLFMF/__init__.py
PyLFMF/_cppkernel/_cppkernel.cpython-39-x86_64-linux-gnu.so
PyLFMF/_cppkernel/__init__.py
