Metadata-Version: 2.1
Name: PyLFMF
Version: 1.1.1
Summary: A wrapper for NTIA/LFMF's groundwave propagarion tool
Home-page: https://github.com/ksavina/PyLFMF/
Author: Kirill Savina & Daniel Sherstnev
Author-email: ksavina@nes.ru
License: UNKNOWN
Platform: UNKNOWN
